automate/__init__.py
automate/callable.py
automate/common.py
automate/namespace.py
automate/program.py
automate/service.py
automate/statusobject.py
automate/system.py
automate/systemobject.py
automate/test_utils.py
automate/tools.py
automate/traits_fixes.py
automate/worker.py
automate/actuators/__init__.py
automate/actuators/builtin_actuators.py
automate/callables/__init__.py
automate/callables/builtin_callables.py
automate/extensions/__init__.py
automate/extensions/arduino/__init__.py
automate/extensions/arduino/arduino_actuators.py
automate/extensions/arduino/arduino_callables.py
automate/extensions/arduino/arduino_sensors.py
automate/extensions/arduino/arduino_service.py
automate/extensions/rpc/__init__.py
automate/extensions/rpc/rpc.py
automate/extensions/rpc/wsgi_xmlrpc.py
automate/extensions/rpio/__init__.py
automate/extensions/rpio/rpio_actuators.py
automate/extensions/rpio/rpio_sensors.py
automate/extensions/rpio/rpio_service.py
automate/extensions/webui/__init__.py
automate/extensions/webui/settings.py
automate/extensions/webui/webui.py
automate/extensions/webui/djangoapp/__init__.py
automate/extensions/webui/djangoapp/forms.py
automate/extensions/webui/djangoapp/urls.py
automate/extensions/webui/djangoapp/views.py
automate/extensions/webui/djangoapp/templates/__init__.py
automate/extensions/webui/djangoapp/templates/base.html
automate/extensions/webui/djangoapp/templates/edit_object.html
automate/extensions/webui/djangoapp/templates/info_panel.html
automate/extensions/webui/djangoapp/templates/login.html
automate/extensions/webui/djangoapp/templates/mocked_services.html
automate/extensions/webui/djangoapp/templates/slider.html
automate/extensions/webui/djangoapp/templates/rows/__init__.py
automate/extensions/webui/djangoapp/templates/rows/actuator_row.html
automate/extensions/webui/djangoapp/templates/rows/general_row.html
automate/extensions/webui/djangoapp/templates/rows/program_row.html
automate-0.10.19.dist-info/DESCRIPTION.rst
automate-0.10.19.dist-info/METADATA
automate-0.10.19.dist-info/RECORD
automate-0.10.19.dist-info/WHEEL
automate-0.10.19.dist-info/entry_points.txt
automate-0.10.19.dist-info/metadata.json
automate-0.10.19.dist-info/top_level.txt
