Metadata-Version: 2.0
Name: automate
Version: 0.10.19
Summary: General purpose Python automatization library with nifty real-time web UI
Home-page: http://github.com/tuomas2/automate
Author: Tuomas Airaksinen
Author-email: tuomas.airaksinen@gmail.com
License: GPL
Download-URL: https://pypi.python.org/pypi/automate
Keywords: automation,GPIO,Raspberry Pi,RPIO,traits
Platform: any
Classifier: Development Status :: 4 - Beta
Classifier: Environment :: Console
Classifier: Environment :: Web Environment
Classifier: Intended Audience :: Education
Classifier: Intended Audience :: End Users/Desktop
Classifier: Intended Audience :: Developers
Classifier: Intended Audience :: Information Technology
Classifier: License :: OSI Approved :: GNU General Public License (GPL)
Classifier: Operating System :: Microsoft :: Windows
Classifier: Operating System :: POSIX
Classifier: Operating System :: POSIX :: Linux
Classifier: Programming Language :: Python :: 2.7
Classifier: Programming Language :: Python :: 3.6
Classifier: Topic :: Scientific/Engineering
Classifier: Topic :: Software Development
Classifier: Topic :: Software Development :: Libraries
Classifier: Topic :: Software Development :: Libraries :: Application Frameworks
Requires-Dist: ansiconv
Requires-Dist: colorlog
Requires-Dist: croniter (~=0.3.0)
Requires-Dist: future
Requires-Dist: ipython (<6.0)
Requires-Dist: mock
Requires-Dist: pyfirmata
Requires-Dist: pyinotify
Requires-Dist: raven
Requires-Dist: requests
Requires-Dist: traits (~=4.6.0)
Provides-Extra: all
Requires-Dist: Django (~=1.11.0); extra == 'all'
Requires-Dist: RPi.GPIO; extra == 'all'
Requires-Dist: django-crispy-forms (~=1.6.0); extra == 'all'
Requires-Dist: tornado (~=4.5.0); extra == 'all'
Provides-Extra: arduino
Provides-Extra: raspberrypi
Requires-Dist: RPi.GPIO; extra == 'raspberrypi'
Provides-Extra: rpc
Requires-Dist: tornado (~=4.5.0); extra == 'rpc'
Provides-Extra: rpio
Requires-Dist: RPIO; extra == 'rpio'
Provides-Extra: web
Requires-Dist: Django (~=1.11.0); extra == 'web'
Requires-Dist: django-crispy-forms (~=1.6.0); extra == 'web'
Requires-Dist: tornado (~=4.5.0); extra == 'web'
